odd_even_checker/__init__.py
odd_even_checker/odd_even.py
oddoreven_jas-0.1.0.dist-info/licenses/LICENSE
oddoreven_jas-0.1.0.dist-info/METADATA
oddoreven_jas-0.1.0.dist-info/WHEEL
oddoreven_jas-0.1.0.dist-info/top_level.txt
oddoreven_jas-0.1.0.dist-info/RECORD
