Metadata-Version: 2.4
Name: oddoreven-jas
Version: 0.1.0
Summary: A simple package to check if numbers are odd or even
Author-email: Jasin <your-email@example.com>
License: MIT
Project-URL: Homepage, https://pypi.org/project/oddoreven-jas/
Keywords: odd,even,checker,math,numbers
Requires-Python: >=3.7
License-File: LICENSE
Dynamic: license-file
